[   "country":"Indonesia",n]
Daftar Transaksi 
No
Lini Jasa
Nama Proyek 
Negara
Tanggal Proyek Dimulai
Status
Klien
Nilai 
1

Manajemen Inisiatif dan Dukungan Perusahaan 

Pemantauan Portofolio Perusahaan Telekomunikasi 
    "country":"Indonesia",
Maret 2019
Sedang berjalan 
Rahasia 
    "value":"N/A",
2
Restrukturisasi Utang dan Manajemen Turnaround 
Restrukturisasi Surat Obligasi Perusahaan OSV Singapura
Singapapura
Maret 2019
Sedang berjalan
Miclyn Express Offshore Limited
    "value":"USD 450 Juta
3
Penasihat M&A
Proyeksi Finansial dan Analisa Modal Kerja Perusahaan Infrastruktur
Singapapura
Maret 2019
Sedang berjalan 
Rahasia 
    "value":"USD 3 Miliar
4
Manajemen Inisiatif dan Dukungan Perusahaan 
Pengembangan Rencana Bisnis Kawasan Industri 
    "country":"Indonesia",
Februari 2019
Sedang berjalan 
Rahasia 
    "value":"USD 1 Miliar
5
Penggalangan Dana 
Manajemen Proyek & Penggalangan Dana Perusahaan Start Up
    "country":"Indonesia",
Maret 2019
Sedang berjalan 
GoHalalGo
    "value":"N/A",
6
Manajemen Inisiatif dan Dukungan Perusahaan
Konsultasi Perusahaan Global dalam Pelaporan Finansial Terintegrasi sebagai Persiapan Penggalangan Modal
Singapapura
Oktober 2018
Selesai 
Rahasia 
    "value":"USD 80 Juta
7
Restrukturisasi Utang dan Manajemen Turnaround
Restrukturisasi Utang Perusahaan Batu Bara
    "country":"Indonesia",
September 2018
Selesai 
(Desember 2018)
Rahasia 
    "value":"USD 60 Juta
8
Restrukturisasi Utang dan Manajemen Turnaround 
Restrukturisasi Utang Perusahaan LPG
    "country":"Indonesia",
Agustus 2018
Sedang berjalan
Rahasia 
    "value":"USD 40 Juta
9
Restrukturisasi Utang dan Manajemen Turnaround 
PKPU Perusahaan Pembiayaan
    "country":"Indonesia",
Agustus 2018
Selesai
(Oktober 2018)
PT Sunprima Nusantara Pembiayaan
    "value":"IDR 4.1 Triliun
10
Restrukturisasi Utang dan Manajemen Turnaround 
Restrukturisasi Utang Perusahaan Card
    "country":"Indonesia",
Juli 2018
Sedang berjalan
Rahasia
    "value":"IDR 840 Miliar
11
Restrukturisasi Utang dan Manajemen Turnaround 
Restrukturisasi Utang Perusahaan Pengeboran Minyak & Gas
    "country":"Indonesia",
Juli 2018
Sedang berjalan
PT Apexindo Pratama Duta Tbk
    "value":"USD 319.7 Juta
12
Restrukturisasi Utang dan Manajemen Turnaround 
PKPU Perusahaan Manufaktur Botol Plastik II
    "country":"Indonesia",
Juni 2018
Selesai 
(Juli 2018)
PT Namasindo Plas Abadi & Afiliasi
    "value":"IDR 1.7 Triliun
13
Restrukturisasi Utang dan Manajemen Turnaround
Penasihat Pemegang Surat Obligasi dari Perusahaan Perkapalan 
Singapapura
Juni 2018
Selesai (November 2018)
Rahasia 
SGD 100 Juta
14
Kepailitan 
Penutupan Sukarela Perusahaan Asuransi UK (diadakan melalui Singapura) 
Singapapura
Mei 2018
Selesai 
(Januari 2019)
Rahasia
    "value":"N/A",
15
Kepailitan 
Representatif Asia dan Agen Likuidasi dari Wali Amanat Kepailitan Amerika Serikat (United States Bankruptcy Trustee) (Chapter 7) 
Singapapura
Februari 2018
Sedang berjalan
Zetta Jet Pte Ltd
    "value":"N/A",
16
Restrukturisasi Utang dan Manajemen Turnaround 
PKPU Perusahaan Manufaktur Botol Plastik I
    "country":"Indonesia",
Februari 2018
Selesai
(Mei 2018)
PT Namasindo Plas 
    "value":"IDR 3.9 Triliun 
17
Restrukturisasi Utang dan Manajemen Turnaround 
Pemantauan Kas Perusahaan LPG
    "country":"Indonesia",
Desember 2017
Sedang berjalan
Rahasia 
    "value":"USD 92.5 Juta 
18
Manajemen Inisiatif dan Dukungan Perusahaan 
Uji Tuntas Komersil Perusahaan Distribusi Gas
    "country":"Indonesia",
November 2017
Selesai
(April 2018)
Rahasia 
    "value":"N/A",
19
Manajemen Inisiatif dan Dukungan Perusahaan
Valuasi terhadap Instrumen Kewajiban Kontinjensi
    "country":"Indonesia",
September 2017
Selesai 
(Januari 2018)
Rahasia 
    "value":"USD 100 Juta
20
Restrukturisasi Utang dan Manajemen Turnaround
Implementasi PKPU: Manajemen Turnaround dan Chief Restructuring Officer
    "country":"Indonesia",
Agustus 2017
Sedang berjalan
Sujaya Group 
    "value":"IDR 3.2 Triliun
21
Kepailitan 
Kurator dan Pendanaan Litigasi oleh Pihak Ketiga
Singapapura
Juli 2017
Sedang berjalan
Trikomsel Singapore Pte Ltd (dalam likuidasi)
SGD 225 Juta
22
Restrukturisasi Utang dan Manajemen Turnaround 
Restrukturisasi Utang Perusahaan LPG 
    "country":"Indonesia",
Mei 2017
Selesai 
(Maret 2018)
Rahasia 
    "value":"USD 92.5 Juta
23
Manajemen Inisiatif dan Dukungan Perusahaan 
Penerbitan Ekuitas dan Obligasi Wajib Konversi
    "country":"Indonesia",
April 2017
Selesai
(Juli 2017)
PT. Bumi Resources Tbk 
    "value":"USD 2.6 Miliar
24
Kepailitan 
Kurator untuk Perusahaan Perkapalan 
Singapapura
Januari 2017
Sedang berjalan 
Siva Ships International Pte Limited (dalam likuidasi)
    "value":"USD 3 Miliar
25
Kepailitan 
Kurator untuk Perusahaan Perkapalan
Singapapura
Desember 2016
Sedang berjalan
Siva Bulk Limited (dalam likuidasi)
    "value":"USD 3 Miyar
26
Kepailitan 
Likuidator dari Perusahaan Transportasi (Ride Hailing) di Singapura
Singapapura
November 2016
Selesai (Desember 2017)
Karhoo Singapore Pte Ltd
    "value":"N/A",
27
Restrukturisasi Utang dan Manajemen Turnaround
PKPU Perusahaan Peternakan dan Pakan Ternak
    "country":"Indonesia",
Oktober 2016
Selesai
(Juli 2017)
Sujaya Group
    "value":"IDR 3.2 Triliun
28
Penasihat M&A
Konsultasi M&A Perusahaan Gas
    "country":"Indonesia",
Juli 2016
Selesai  
(Januari 2017)
Rahasia 
    "value":"N/A",
29
Penggalangan Dana 
Restrukturisasi Korporat dan Penggalangan Dana atas Perusahaan Teknologi Bantuan Reproduksi
    "country":"Indonesia",
Mei 2016
Sedang berjalan 
Rahasia
    "value":"N/A",
30
Pendukung dan Penasihat Kreditor
Penasihat Kreditur dari Perusahaan Penggilingan Gula di Vietnam
Singapapura
April 2016
Selesai 
(Juni 2017)
Rahasia 
    "value":"USD 250 Juta 
31
Restrukturisasi Utang dan Manajemen Turnaround
PKPU Perusahaan Batubara 
    "country":"Indonesia",
April 2016
Selesai
(November 2016)
PT. Bumi Resources Tbk 
    "value":"USD 7 Miliar 
32
Restrukturisasi Utang dan Manajemen Turnaround
PKPU Perusahaan Pengemasan 
    "country":"Indonesia",
April 2016
Selesai  
(Januari 2017)
PT. Dwi Aneka Jaya Kemasindo Tbk 
    "value":"IDR 1.2 Triliun
33
Pendukung dan Penasihat Kreditor
Penasihat Kreditor dalam Restrukrisasi Utang Perusahaan Daya
    "country":"Indonesia",
April 2016
Selesai  
(Juni 2017)
Rahasia  
    "value":"USD 191.3 Juta 
34
Penasihat M&A
Konsultansi Sisi Jual Perusahaan Gerbang Pembayaran 
    "country":"Indonesia",
April 2016
Selesai 
(Juli 2018)
Rahasia 
    "value":"N/A",
35
Penggalanan Dana 
Penggalanan Dana Perusahaan CNG/LNG Companies
    "country":"Indonesia",
Januari 2016
Selesai 
 (January 2017)
Rahasia
    "value":"N/A",
36
Restrukturisasi Utang dan Manajemen Turnaround
Dukungan Implementasi Transaksi PKPU Perusahaan Perkebunan dan Perdagangan Teh
    "country":"Indonesia",
November 2015
Selesai 
(Maret 2016)
PT. Sariwangi Agriculture Estates Agency
    "value":"USD 107 Juta
37
Pendukung dan Penasihat Kreditor
Dukungan dan Konsultansi Kreditor Perusahaan Batubara
    "country":"Indonesia",
Juli 2015
Selesai  
(Maret 2016)
Rahasia 
    "value":"USD 25 Juta 
38
Manajemen Inisiatif dan Dukungan Perusahaan
Dukungan Transaksi Akuisisi Saham dan Surat Utang Perusahaan Petrokimia 
    "country":"Indonesia",
Juni 2015
Selesai 
(Oktober 2015)
Rahasia 
    "value":"USD 290 Juta
39
Restrukturisasi Utang dan Manajemen Turnaround
Restrukturisasi Utang Perusahaan Otomotif 
    "country":"Indonesia",
Mei 2015
Selesai  (Desember 2015)
Rahasia 
    "value":"IDR 200 Miliar 
40
Restrukturisasi Utang dan Manajemen Turnaround
PKPU Perusahaan Perkebunan dan Perdagangan teh 
    "country":"Indonesia",
Mei 2015
Selesai  
(Oktober 2015)
PT. Sariwangi Agricultural Estates Agency 
    "value":"USD 107 Juta
41
Manajemen Inisiatif dan Dukungan Perusahaan 
Uji Tuntas Komersil Perusahaan Perabotan 
    "country":"Indonesia",
Januari 2015
Selesai 
(Oktober 2015)
Rahasia 
    "value":"N/A",

42
Restrukturisasi Utang dan Manajemen Turnaround
PKPU Perusahaan Telekomunikasi  
    "country":"Indonesia",
Oktober 2014
Selesai  (Desember 2014)
PT. Bakrie Telecom Tbk. 
    "value":"IDR 12 Triliun

43
Restrukturisasi Utang dan Manajemen Turnaround
Dukungan Implementasi Transaksi PKPU Perusahaan Petrokimia  
    "country":"Indonesia",
Februari 2013
Selesai (Desember 2014)
PT. Trans-Pacific Petrochemical     "country":"Indonesia", 
    "value":"USD 1.5 Miliar 
44
Penggalangan Dana 
Penggalangan Dana Produsen Bahan Mentah Alami Makanan 
    "country":"Indonesia",
Februari 2013
Selesai 
(Maret 2014)
Rahasia 
    "value":"USD 31.5 Juta 
45
Manajemen Inisiatif dan Dukungan Perusahaan 
Layanan Valuasi untuk Perusahaan Batubara
    "country":"Indonesia",
Januari 2013
Selesai 
(Mei 2013)
PT. Sembawang Development PTE. LTD. 
    "value":"USD 111 Juta
46
Restrukturisasi Utang dan Manajemen Turnaround
PKPU Perusahaan Petrokimia 
    "country":"Indonesia",
November 2012
Selesai
 (Desember 2012)
PT. Trans-Pacific Petrochemical     "country":"Indonesia",
    "value":"USD 1.9 Miliar
47
Penggalanan Dana 
Penggalanan Dana Perusahaan Jalan Tol  
    "country":"Indonesia",
Juni 2011
Selesai  
(August 2013)
Rahasia 
    "value":"IDR 5 Triliun 
48
Restrukturisasi Utang dan Manajemen Turnaround
PKPU Maskapai Penerbangan 
    "country":"Indonesia",
April 2011
Selesai 
(Agustus 2011)
PT. Mandala Airlines 
    "value":"IDR 2.5 Triliun
49
Penasihat M&A
Dukungan Akuisisi atas Perusahaan Batubara 
    "country":"Indonesia",
Oktober 2010
Selesai  
(Maret 2011)
PT. Bumi Resources Tbk
    "value":"USD 3 Miliar
50
Penasihat M&A
Akuisisi Perusahaan Layanan Direktori dan Call Center 
    "country":"Indonesia",
Februari 2008
Selesai 
(Juni 2009)
    "client":"PT. Multimedia Nusantara",
    "value":"IDR 598 Miliar
51
Penasihat M&A
Akuisisi Perusahaan Administrator Pihak Ketiga untuk Asuransi 
    "country":"Indonesia",
Maret 2008
Selesai 
(Juli 2008)
    "client":"PT. Multimedia Nusantara",
    "value":"   "value":"IDR 128 Miliar",
}]